{
  "$schema": "./node_modules/@biomejs/biome/configuration_schema.json",
  "files": {
    "includes": [
      "**/*",
      "!.astro/*",
      "!src/@types/*",
      "!public/api-schemas.json",
      "!public/cli-schema.json",
      "!public/mergify-configuration-schema.json",
      "!dist/*",
      "!**/*.svg"
    ]
  },
  "formatter": {
    "enabled": true,
    "formatWithErrors": false,
    "indentStyle": "space",
    "indentWidth": 2,
    "lineEnding": "lf",
    "lineWidth": 100,
    "attributePosition": "auto"
  },
  "linter": { "enabled": false },
  "css": { "parser": { "cssModules": true } },
  "javascript": {
    "formatter": {
      "jsxQuoteStyle": "double",
      "quoteProperties": "asNeeded",
      "trailingCommas": "es5",
      "semicolons": "always",
      "arrowParentheses": "always",
      "bracketSpacing": true,
      "bracketSameLine": false,
      "quoteStyle": "single",
      "attributePosition": "auto"
    }
  }
}
